muxsim/__init__.py
muxsim/gen.py
muxsim-0.1.1.dist-info/METADATA
muxsim-0.1.1.dist-info/WHEEL
muxsim-0.1.1.dist-info/licenses/LICENSE
muxsim-0.1.1.dist-info/RECORD
