Metadata-Version: 2.3
Name: muxsim
Version: 0.1.1
Summary: A tool to simulate cell/guide matrices
Author: Noam Teyssier
License-File: LICENSE
Requires-Python: >=3.11
Requires-Dist: matplotlib>=3.9.2
Requires-Dist: numpy>=2.1.2
Requires-Dist: pandas>=2.2.3
Requires-Dist: scipy>=1.14.1
Requires-Dist: seaborn>=0.13.2
Requires-Dist: tqdm>=4.66.5
